dgkafka/__init__.py
dgkafka/avro_consumer.py
dgkafka/avro_producer.py
dgkafka/config.py
dgkafka/consumer.py
dgkafka/errors.py
dgkafka/json_consumer.py
dgkafka/producer.py
dgkafka-1.0.1.dist-info/licenses/LICENSE
dgkafka-1.0.1.dist-info/METADATA
dgkafka-1.0.1.dist-info/WHEEL
dgkafka-1.0.1.dist-info/top_level.txt
dgkafka-1.0.1.dist-info/RECORD
