Metadata-Version: 2.4
Name: dgkafka
Version: 1.0.1
Summary: Kafka clients
Home-page: https://gitlab.com/gng-group/dgkafka.git
Author: Malanris
Author-email: Roman Rasputin <admin@roro.su>
License: MIT License
Project-URL: Homepage, https://gitlab.com/gng-group/dgkafka
Project-URL: BugTracker, https://gitlab.com/gng-group/dgkafka/issues
Keywords: kafka,client,confluent,avro,fastapi,logging
Classifier: Development Status :: 4 - Beta
Classifier: Intended Audience :: Developers
Classifier: License :: OSI Approved :: MIT License
Classifier: Programming Language :: Python :: 3.10
Classifier: Programming Language :: Python :: 3.11
Classifier: Operating System :: OS Independent
Classifier: Topic :: Software Development :: Libraries :: Python Modules
Classifier: Topic :: System :: Logging
Classifier: Topic :: System :: Distributed Computing
Requires-Python: >=3.10
License-File: LICENSE
Requires-Dist: confluent-kafka>=2.1.1
Requires-Dist: dglog>=1.0.0
Requires-Dist: pydantic
Provides-Extra: avro
Requires-Dist: requests; extra == "avro"
Requires-Dist: fastavro<2; extra == "avro"
Requires-Dist: avro<2,>=1.11.1; extra == "avro"
Requires-Dist: attrs; extra == "avro"
Requires-Dist: cachetools; extra == "avro"
Requires-Dist: httpx>=0.26; extra == "avro"
Requires-Dist: authlib; extra == "avro"
Provides-Extra: json
Requires-Dist: pyrsistent; extra == "json"
Requires-Dist: jsonschema; extra == "json"
Dynamic: author
Dynamic: home-page
Dynamic: license-file
